{
  "__inputs": [
    {
      "name": "DS_INFLUX",
      "label": "Influx",
      "description": "",
      "type": "datasource",
      "pluginId": "influxdb",
      "pluginName": "InfluxDB"
    }
  ],
  "__requires": [
    {
      "type": "grafana",
      "id": "grafana",
      "name": "Grafana",
      "version": "5.1.3"
    },
    {
      "type": "panel",
      "id": "graph",
      "name": "Graph",
      "version": "5.0.0"
    },
    {
      "type": "datasource",
      "id": "influxdb",
      "name": "InfluxDB",
      "version": "5.0.0"
    },
    {
      "type": "panel",
      "id": "singlestat",
      "name": "Singlestat",
      "version": "5.0.0"
    }
  ],
  "annotations": {
    "list": [
      {
        "builtIn": 1,
        "datasource": "-- Grafana --",
        "enable": true,
        "hide": true,
        "iconColor": "rgba(0, 211, 255, 1)",
        "name": "Annotations & Alerts",
        "type": "dashboard"
      }
    ]
  },
  "editable": true,
  "gnetId": 8003,
  "graphTooltip": 1,
  "id": null,
  "iteration": 1537346350268,
  "links": [],
  "panels": [
    {
      "collapsed": false,
      "gridPos": {
        "h": 1,
        "w": 24,
        "x": 0,
        "y": 0
      },
      "id": 42,
      "panels": [],
      "title": "Quick Overview",
      "type": "row"
    },
    {
      "cacheTimeout": null,
      "colorBackground": false,
      "colorValue": true,
      "colors": [
        "#299c46",
        "rgba(237, 129, 40, 0.89)",
        "#d44a3a"
      ],
      "datasource": "${DS_INFLUX}",
      "format": "percent",
      "gauge": {
        "maxValue": 100,
        "minValue": 0,
        "show": true,
        "thresholdLabels": false,
        "thresholdMarkers": true
      },
      "gridPos": {
        "h": 5,
        "w": 5,
        "x": 0,
        "y": 1
      },
      "id": 44,
      "interval": null,
      "links": [],
      "mappingType": 1,
      "mappingTypes": [
        {
          "name": "value to text",
          "value": 1
        },
        {
          "name": "range to text",
          "value": 2
        }
      ],
      "maxDataPoints": 100,
      "minSpan": 4,
      "nullPointMode": "connected",
      "nullText": null,
      "postfix": "",
      "postfixFontSize": "50%",
      "prefix": "",
      "prefixFontSize": "50%",
      "rangeMaps": [
        {
          "from": "null",
          "text": "N/A",
          "to": "null"
        }
      ],
      "repeat": null,
      "repeatDirection": "h",
      "sparkline": {
        "fillColor": "rgba(31, 118, 189, 0.18)",
        "full": false,
        "lineColor": "rgb(31, 120, 193)",
        "show": false
      },
      "tableColumn": "mean",
      "targets": [
        {
          "groupBy": [
            {
              "params": [
                "$__interval"
              ],
              "type": "time"
            },
            {
              "params": [
                "null"
              ],
              "type": "fill"
            }
          ],
          "measurement": "LINUX_VMSTAT",
          "orderByTime": "ASC",
          "policy": "default",
          "refId": "A",
          "resultFormat": "time_series",
          "select": [
            [
              {
                "params": [
                  "value"
                ],
                "type": "field"
              },
              {
                "params": [],
                "type": "mean"
              }
            ]
          ],
          "tags": [
            {
              "key": "host",
              "operator": "=~",
              "value": "/^$host$/"
            },
            {
              "condition": "AND",
              "key": "type",
              "operator": "=",
              "value": "SystemCPU"
            }
          ]
        }
      ],
      "thresholds": "100,50,20",
      "title": "System CPU Usage",
      "type": "singlestat",
      "valueFontSize": "80%",
      "valueMaps": [
        {
          "op": "=",
          "text": "N/A",
          "value": "null"
        }
      ],
      "valueName": "current"
    },
    {
      "cacheTimeout": null,
      "colorBackground": false,
      "colorValue": true,
      "colors": [
        "#299c46",
        "rgba(237, 129, 40, 0.89)",
        "#d44a3a"
      ],
      "datasource": "${DS_INFLUX}",
      "format": "percent",
      "gauge": {
        "maxValue": 100,
        "minValue": 0,
        "show": true,
        "thresholdLabels": false,
        "thresholdMarkers": true
      },
      "gridPos": {
        "h": 5,
        "w": 5,
        "x": 5,
        "y": 1
      },
      "id": 47,
      "interval": null,
      "links": [],
      "mappingType": 1,
      "mappingTypes": [
        {
          "name": "value to text",
          "value": 1
        },
        {
          "name": "range to text",
          "value": 2
        }
      ],
      "maxDataPoints": 100,
      "minSpan": 4,
      "nullPointMode": "connected",
      "nullText": null,
      "postfix": "",
      "postfixFontSize": "50%",
      "prefix": "",
      "prefixFontSize": "50%",
      "rangeMaps": [
        {
          "from": "null",
          "text": "N/A",
          "to": "null"
        }
      ],
      "repeatDirection": "h",
      "sparkline": {
        "fillColor": "rgba(31, 118, 189, 0.18)",
        "full": false,
        "lineColor": "rgb(31, 120, 193)",
        "show": false
      },
      "tableColumn": "mean",
      "targets": [
        {
          "groupBy": [
            {
              "params": [
                "$__interval"
              ],
              "type": "time"
            },
            {
              "params": [
                "null"
              ],
              "type": "fill"
            }
          ],
          "measurement": "LINUX_VMSTAT",
          "orderByTime": "ASC",
          "policy": "default",
          "refId": "A",
          "resultFormat": "time_series",
          "select": [
            [
              {
                "params": [
                  "value"
                ],
                "type": "field"
              },
              {
                "params": [],
                "type": "mean"
              }
            ]
          ],
          "tags": [
            {
              "key": "host",
              "operator": "=~",
              "value": "/^$host$/"
            },
            {
              "condition": "AND",
              "key": "type",
              "operator": "=",
              "value": "UserCPU"
            }
          ]
        }
      ],
      "thresholds": "100,50,20",
      "title": "User CPU Usage",
      "type": "singlestat",
      "valueFontSize": "80%",
      "valueMaps": [
        {
          "op": "=",
          "text": "N/A",
          "value": "null"
        }
      ],
      "valueName": "current"
    },
    {
      "cacheTimeout": null,
      "colorBackground": false,
      "colorValue": true,
      "colors": [
        "#299c46",
        "rgba(237, 129, 40, 0.89)",
        "#d44a3a"
      ],
      "datasource": "${DS_INFLUX}",
      "format": "percent",
      "gauge": {
        "maxValue": 100,
        "minValue": 0,
        "show": true,
        "thresholdLabels": false,
        "thresholdMarkers": true
      },
      "gridPos": {
        "h": 5,
        "w": 5,
        "x": 10,
        "y": 1
      },
      "id": 45,
      "interval": null,
      "links": [],
      "mappingType": 1,
      "mappingTypes": [
        {
          "name": "value to text",
          "value": 1
        },
        {
          "name": "range to text",
          "value": 2
        }
      ],
      "maxDataPoints": 100,
      "minSpan": 4,
      "nullPointMode": "connected",
      "nullText": null,
      "postfix": "",
      "postfixFontSize": "50%",
      "prefix": "",
      "prefixFontSize": "50%",
      "rangeMaps": [
        {
          "from": "null",
          "text": "N/A",
          "to": "null"
        }
      ],
      "repeatDirection": "h",
      "sparkline": {
        "fillColor": "rgba(31, 118, 189, 0.18)",
        "full": false,
        "lineColor": "rgb(31, 120, 193)",
        "show": false
      },
      "tableColumn": "mean",
      "targets": [
        {
          "groupBy": [
            {
              "params": [
                "$__interval"
              ],
              "type": "time"
            },
            {
              "params": [
                "null"
              ],
              "type": "fill"
            }
          ],
          "measurement": "LINUX_TOP_MEM",
          "orderByTime": "ASC",
          "policy": "default",
          "refId": "A",
          "resultFormat": "time_series",
          "select": [
            [
              {
                "params": [
                  "value"
                ],
                "type": "field"
              },
              {
                "params": [],
                "type": "mean"
              }
            ]
          ],
          "tags": [
            {
              "key": "host",
              "operator": "=~",
              "value": "/^$host$/"
            }
          ]
        }
      ],
      "thresholds": "100,50,20",
      "title": "Memory Usage",
      "type": "singlestat",
      "valueFontSize": "80%",
      "valueMaps": [
        {
          "op": "=",
          "text": "N/A",
          "value": "null"
        }
      ],
      "valueName": "current"
    },
    {
      "cacheTimeout": null,
      "colorBackground": false,
      "colorValue": true,
      "colors": [
        "#299c46",
        "rgba(237, 129, 40, 0.89)",
        "#d44a3a"
      ],
      "datasource": "${DS_INFLUX}",
      "format": "percent",
      "gauge": {
        "maxValue": 100,
        "minValue": 0,
        "show": true,
        "thresholdLabels": false,
        "thresholdMarkers": true
      },
      "gridPos": {
        "h": 5,
        "w": 5,
        "x": 15,
        "y": 1
      },
      "id": 46,
      "interval": null,
      "links": [],
      "mappingType": 1,
      "mappingTypes": [
        {
          "name": "value to text",
          "value": 1
        },
        {
          "name": "range to text",
          "value": 2
        }
      ],
      "maxDataPoints": 100,
      "minSpan": 4,
      "nullPointMode": "connected",
      "nullText": null,
      "postfix": "",
      "postfixFontSize": "50%",
      "prefix": "",
      "prefixFontSize": "50%",
      "rangeMaps": [
        {
          "from": "null",
          "text": "N/A",
          "to": "null"
        }
      ],
      "repeatDirection": "h",
      "sparkline": {
        "fillColor": "rgba(31, 118, 189, 0.18)",
        "full": false,
        "lineColor": "rgb(31, 120, 193)",
        "show": false
      },
      "tableColumn": "mean",
      "targets": [
        {
          "groupBy": [
            {
              "params": [
                "$__interval"
              ],
              "type": "time"
            },
            {
              "params": [
                "null"
              ],
              "type": "fill"
            }
          ],
          "measurement": "LINUX_IOSTAT",
          "orderByTime": "ASC",
          "policy": "default",
          "refId": "A",
          "resultFormat": "time_series",
          "select": [
            [
              {
                "params": [
                  "value"
                ],
                "type": "field"
              },
              {
                "params": [],
                "type": "mean"
              }
            ]
          ],
          "tags": [
            {
              "key": "host",
              "operator": "=~",
              "value": "/^$host$/"
            }
          ]
        }
      ],
      "thresholds": "100,50,20",
      "title": "Disk Usage",
      "type": "singlestat",
      "valueFontSize": "80%",
      "valueMaps": [
        {
          "op": "=",
          "text": "N/A",
          "value": "null"
        }
      ],
      "valueName": "current"
    },
    {
      "cacheTimeout": null,
      "colorBackground": false,
      "colorValue": true,
      "colors": [
        "#299c46",
        "rgba(237, 129, 40, 0.89)",
        "#d44a3a"
      ],
      "datasource": "${DS_INFLUX}",
      "format": "percent",
      "gauge": {
        "maxValue": 100,
        "minValue": 0,
        "show": true,
        "thresholdLabels": false,
        "thresholdMarkers": true
      },
      "gridPos": {
        "h": 5,
        "w": 4,
        "x": 20,
        "y": 1
      },
      "id": 48,
      "interval": null,
      "links": [],
      "mappingType": 1,
      "mappingTypes": [
        {
          "name": "value to text",
          "value": 1
        },
        {
          "name": "range to text",
          "value": 2
        }
      ],
      "maxDataPoints": 100,
      "minSpan": 4,
      "nullPointMode": "connected",
      "nullText": null,
      "postfix": "",
      "postfixFontSize": "50%",
      "prefix": "",
      "prefixFontSize": "50%",
      "rangeMaps": [
        {
          "from": "null",
          "text": "N/A",
          "to": "null"
        }
      ],
      "repeatDirection": "h",
      "sparkline": {
        "fillColor": "rgba(31, 118, 189, 0.18)",
        "full": false,
        "lineColor": "rgb(31, 120, 193)",
        "show": false
      },
      "tableColumn": "mean",
      "targets": [
        {
          "groupBy": [
            {
              "params": [
                "$__interval"
              ],
              "type": "time"
            },
            {
              "params": [
                "null"
              ],
              "type": "fill"
            }
          ],
          "measurement": "LINUX_IOSTAT",
          "orderByTime": "ASC",
          "policy": "default",
          "refId": "A",
          "resultFormat": "time_series",
          "select": [
            [
              {
                "params": [
                  "value"
                ],
                "type": "field"
              },
              {
                "params": [],
                "type": "mean"
              }
            ]
          ],
          "tags": [
            {
              "key": "host",
              "operator": "=~",
              "value": "/^$host$/"
            }
          ]
        }
      ],
      "thresholds": "100,50,20",
      "title": "Disk Usage",
      "type": "singlestat",
      "valueFontSize": "80%",
      "valueMaps": [
        {
          "op": "=",
          "text": "N/A",
          "value": "null"
        }
      ],
      "valueName": "current"
    },
    {
      "collapsed": false,
      "gridPos": {
        "h": 1,
        "w": 24,
        "x": 0,
        "y": 6
      },
      "id": 38,
      "panels": [],
      "title": "Network Stats",
      "type": "row"
    },
    {
      "aliasColors": {},
      "bars": false,
      "dashLength": 10,
      "dashes": false,
      "datasource": "${DS_INFLUX}",
      "fill": 1,
      "gridPos": {
        "h": 9,
        "w": 12,
        "x": 0,
        "y": 7
      },
      "id": 22,
      "legend": {
        "avg": false,
        "current": false,
        "max": false,
        "min": false,
        "show": true,
        "total": false,
        "values": false
      },
      "lines": true,
      "linewidth": 1,
      "links": [],
      "nullPointMode": "null",
      "percentage": false,
      "pointradius": 1,
      "points": true,
      "renderer": "flot",
      "seriesOverrides": [],
      "spaceLength": 10,
      "stack": false,
      "steppedLine": false,
      "targets": [
        {
          "groupBy": [
            {
              "params": [
                "$__interval"
              ],
              "type": "time"
            },
            {
              "params": [
                "type"
              ],
              "type": "tag"
            },
            {
              "params": [
                "deviceid"
              ],
              "type": "tag"
            }
          ],
          "measurement": "LINUX_NETSTAT",
          "orderByTime": "ASC",
          "policy": "default",
          "query": "SELECT mean(\"value\") FROM \"LINUX_NETSTAT\" WHERE (\"host\" =~ /^$host$/) AND $timeFilter GROUP BY time($__interval), \"host\", \"type\"",
          "rawQuery": false,
          "refId": "A",
          "resultFormat": "time_series",
          "select": [
            [
              {
                "params": [
                  "value"
                ],
                "type": "field"
              },
              {
                "params": [],
                "type": "mean"
              }
            ]
          ],
          "tags": [
            {
              "key": "host",
              "operator": "=~",
              "value": "/^$host$/"
            }
          ],
          "target": ""
        }
      ],
      "thresholds": [],
      "timeFrom": null,
      "timeShift": null,
      "title": "LINUX_NETSTAT",
      "tooltip": {
        "shared": true,
        "sort": 0,
        "value_type": "individual"
      },
      "type": "graph",
      "xaxis": {
        "buckets": null,
        "mode": "time",
        "name": null,
        "show": true,
        "values": []
      },
      "yaxes": [
        {
          "format": "short",
          "label": null,
          "logBase": 1,
          "max": null,
          "min": null,
          "show": true
        },
        {
          "format": "short",
          "label": null,
          "logBase": 1,
          "max": null,
          "min": null,
          "show": true
        }
      ],
      "yaxis": {
        "align": false,
        "alignLevel": null
      }
    },
    {
      "aliasColors": {},
      "bars": false,
      "dashLength": 10,
      "dashes": false,
      "datasource": "${DS_INFLUX}",
      "fill": 1,
      "gridPos": {
        "h": 9,
        "w": 12,
        "x": 12,
        "y": 7
      },
      "id": 26,
      "legend": {
        "avg": true,
        "current": false,
        "max": true,
        "min": false,
        "show": true,
        "total": false,
        "values": true
      },
      "lines": true,
      "linewidth": 1,
      "links": [],
      "nullPointMode": "null",
      "percentage": false,
      "pointradius": 5,
      "points": false,
      "renderer": "flot",
      "seriesOverrides": [],
      "spaceLength": 10,
      "stack": false,
      "steppedLine": false,
      "targets": [
        {
          "groupBy": [
            {
              "params": [
                "host"
              ],
              "type": "tag"
            },
            {
              "params": [
                "type"
              ],
              "type": "tag"
            }
          ],
          "measurement": "WIN_NETSTAT",
          "orderByTime": "ASC",
          "policy": "default",
          "refId": "A",
          "resultFormat": "time_series",
          "select": [
            [
              {
                "params": [
                  "value"
                ],
                "type": "field"
              }
            ]
          ],
          "tags": [],
          "target": ""
        }
      ],
      "thresholds": [],
      "timeFrom": null,
      "timeShift": null,
      "title": "WIN-NETWORK",
      "tooltip": {
        "shared": true,
        "sort": 0,
        "value_type": "individual"
      },
      "type": "graph",
      "xaxis": {
        "buckets": null,
        "mode": "time",
        "name": null,
        "show": true,
        "values": []
      },
      "yaxes": [
        {
          "format": "short",
          "label": null,
          "logBase": 1,
          "max": null,
          "min": null,
          "show": true
        },
        {
          "format": "short",
          "label": null,
          "logBase": 1,
          "max": null,
          "min": null,
          "show": true
        }
      ],
      "yaxis": {
        "align": false,
        "alignLevel": null
      }
    },
    {
      "collapsed": false,
      "gridPos": {
        "h": 1,
        "w": 24,
        "x": 0,
        "y": 16
      },
      "id": 36,
      "panels": [],
      "title": "I/O Stats",
      "type": "row"
    },
    {
      "aliasColors": {},
      "bars": false,
      "dashLength": 10,
      "dashes": false,
      "datasource": "${DS_INFLUX}",
      "fill": 1,
      "gridPos": {
        "h": 9,
        "w": 12,
        "x": 0,
        "y": 17
      },
      "id": 20,
      "legend": {
        "avg": true,
        "current": false,
        "max": true,
        "min": false,
        "show": true,
        "total": false,
        "values": true
      },
      "lines": true,
      "linewidth": 1,
      "links": [],
      "nullPointMode": "null",
      "percentage": false,
      "pointradius": 1,
      "points": true,
      "renderer": "flot",
      "seriesOverrides": [],
      "spaceLength": 10,
      "stack": false,
      "steppedLine": false,
      "targets": [
        {
          "groupBy": [
            {
              "params": [
                "$__interval"
              ],
              "type": "time"
            },
            {
              "params": [
                "type"
              ],
              "type": "tag"
            },
            {
              "params": [
                "deviceid"
              ],
              "type": "tag"
            }
          ],
          "measurement": "LINUX_IOSTAT",
          "orderByTime": "ASC",
          "policy": "default",
          "refId": "A",
          "resultFormat": "time_series",
          "select": [
            [
              {
                "params": [
                  "value"
                ],
                "type": "field"
              },
              {
                "params": [],
                "type": "mean"
              }
            ]
          ],
          "tags": [
            {
              "key": "host",
              "operator": "=~",
              "value": "/^$host$/"
            }
          ],
          "target": ""
        }
      ],
      "thresholds": [],
      "timeFrom": null,
      "timeShift": null,
      "title": "LINUX_IOSTAT",
      "tooltip": {
        "shared": true,
        "sort": 0,
        "value_type": "individual"
      },
      "type": "graph",
      "xaxis": {
        "buckets": null,
        "mode": "time",
        "name": null,
        "show": true,
        "values": []
      },
      "yaxes": [
        {
          "format": "short",
          "label": null,
          "logBase": 1,
          "max": null,
          "min": null,
          "show": true
        },
        {
          "format": "short",
          "label": null,
          "logBase": 1,
          "max": null,
          "min": null,
          "show": true
        }
      ],
      "yaxis": {
        "align": false,
        "alignLevel": null
      }
    },
    {
      "aliasColors": {},
      "bars": false,
      "dashLength": 10,
      "dashes": false,
      "datasource": "${DS_INFLUX}",
      "fill": 1,
      "gridPos": {
        "h": 9,
        "w": 12,
        "x": 12,
        "y": 17
      },
      "id": 28,
      "legend": {
        "avg": true,
        "current": false,
        "max": true,
        "min": false,
        "show": true,
        "total": false,
        "values": true
      },
      "lines": true,
      "linewidth": 1,
      "links": [],
      "nullPointMode": "null",
      "percentage": false,
      "pointradius": 5,
      "points": false,
      "renderer": "flot",
      "seriesOverrides": [],
      "spaceLength": 10,
      "stack": false,
      "steppedLine": false,
      "targets": [
        {
          "groupBy": [
            {
              "params": [
                "host"
              ],
              "type": "tag"
            },
            {
              "params": [
                "type"
              ],
              "type": "tag"
            }
          ],
          "measurement": "WIN_IOSTAT",
          "orderByTime": "ASC",
          "policy": "default",
          "refId": "A",
          "resultFormat": "time_series",
          "select": [
            [
              {
                "params": [
                  "value"
                ],
                "type": "field"
              }
            ]
          ],
          "tags": [
            {
              "key": "host",
              "operator": "=~",
              "value": "/^$host$/"
            }
          ],
          "target": ""
        }
      ],
      "thresholds": [],
      "timeFrom": null,
      "timeShift": null,
      "title": "WIN-IOSTAT",
      "tooltip": {
        "shared": true,
        "sort": 0,
        "value_type": "individual"
      },
      "type": "graph",
      "xaxis": {
        "buckets": null,
        "mode": "time",
        "name": null,
        "show": true,
        "values": []
      },
      "yaxes": [
        {
          "format": "short",
          "label": null,
          "logBase": 1,
          "max": null,
          "min": null,
          "show": true
        },
        {
          "format": "short",
          "label": null,
          "logBase": 1,
          "max": null,
          "min": null,
          "show": true
        }
      ],
      "yaxis": {
        "align": false,
        "alignLevel": null
      }
    },
    {
      "collapsed": false,
      "gridPos": {
        "h": 1,
        "w": 24,
        "x": 0,
        "y": 26
      },
      "id": 50,
      "panels": [],
      "title": "Memory & VM Stats",
      "type": "row"
    },
    {
      "aliasColors": {},
      "bars": false,
      "dashLength": 10,
      "dashes": false,
      "datasource": "${DS_INFLUX}",
      "fill": 1,
      "gridPos": {
        "h": 9,
        "w": 12,
        "x": 0,
        "y": 27
      },
      "id": 18,
      "legend": {
        "avg": true,
        "current": false,
        "max": true,
        "min": false,
        "show": true,
        "total": false,
        "values": true
      },
      "lines": true,
      "linewidth": 1,
      "links": [],
      "nullPointMode": "null",
      "percentage": false,
      "pointradius": 1,
      "points": true,
      "renderer": "flot",
      "seriesOverrides": [],
      "spaceLength": 10,
      "stack": false,
      "steppedLine": false,
      "targets": [
        {
          "groupBy": [
            {
              "params": [
                "$__interval"
              ],
              "type": "time"
            },
            {
              "params": [
                "type"
              ],
              "type": "tag"
            }
          ],
          "measurement": "LINUX_VMSTAT",
          "orderByTime": "ASC",
          "policy": "default",
          "refId": "A",
          "resultFormat": "time_series",
          "select": [
            [
              {
                "params": [
                  "value"
                ],
                "type": "field"
              },
              {
                "params": [],
                "type": "mean"
              }
            ]
          ],
          "tags": [
            {
              "key": "host",
              "operator": "=~",
              "value": "/^$host$/"
            }
          ],
          "target": ""
        }
      ],
      "thresholds": [],
      "timeFrom": null,
      "timeShift": null,
      "title": "LINUX_VMSTAT",
      "tooltip": {
        "shared": true,
        "sort": 0,
        "value_type": "individual"
      },
      "type": "graph",
      "xaxis": {
        "buckets": null,
        "mode": "time",
        "name": null,
        "show": true,
        "values": []
      },
      "yaxes": [
        {
          "format": "short",
          "label": null,
          "logBase": 1,
          "max": null,
          "min": null,
          "show": true
        },
        {
          "format": "short",
          "label": null,
          "logBase": 1,
          "max": null,
          "min": null,
          "show": true
        }
      ],
      "yaxis": {
        "align": false,
        "alignLevel": null
      }
    },
    {
      "aliasColors": {},
      "bars": false,
      "dashLength": 10,
      "dashes": false,
      "datasource": "${DS_INFLUX}",
      "fill": 1,
      "gridPos": {
        "h": 9,
        "w": 12,
        "x": 12,
        "y": 27
      },
      "id": 24,
      "legend": {
        "avg": true,
        "current": false,
        "max": true,
        "min": false,
        "show": true,
        "total": false,
        "values": true
      },
      "lines": true,
      "linewidth": 1,
      "links": [],
      "nullPointMode": "null",
      "percentage": false,
      "pointradius": 5,
      "points": false,
      "renderer": "flot",
      "seriesOverrides": [],
      "spaceLength": 10,
      "stack": false,
      "steppedLine": false,
      "targets": [
        {
          "groupBy": [
            {
              "params": [
                "host"
              ],
              "type": "tag"
            },
            {
              "params": [
                "type"
              ],
              "type": "tag"
            }
          ],
          "measurement": "WIN_MEM",
          "orderByTime": "ASC",
          "policy": "default",
          "refId": "A",
          "resultFormat": "time_series",
          "select": [
            [
              {
                "params": [
                  "value"
                ],
                "type": "field"
              }
            ]
          ],
          "tags": [],
          "target": ""
        }
      ],
      "thresholds": [],
      "timeFrom": null,
      "timeShift": null,
      "title": "WIN-MEM",
      "tooltip": {
        "shared": true,
        "sort": 0,
        "value_type": "individual"
      },
      "type": "graph",
      "xaxis": {
        "buckets": null,
        "mode": "time",
        "name": null,
        "show": true,
        "values": []
      },
      "yaxes": [
        {
          "format": "decmbytes",
          "label": null,
          "logBase": 1,
          "max": null,
          "min": null,
          "show": true
        },
        {
          "format": "short",
          "label": null,
          "logBase": 1,
          "max": null,
          "min": null,
          "show": true
        }
      ],
      "yaxis": {
        "align": false,
        "alignLevel": null
      }
    },
    {
      "aliasColors": {},
      "bars": false,
      "dashLength": 10,
      "dashes": false,
      "datasource": "${DS_INFLUX}",
      "fill": 1,
      "gridPos": {
        "h": 9,
        "w": 12,
        "x": 0,
        "y": 36
      },
      "id": 34,
      "legend": {
        "avg": true,
        "current": false,
        "max": true,
        "min": false,
        "show": true,
        "total": false,
        "values": true
      },
      "lines": true,
      "linewidth": 1,
      "links": [],
      "nullPointMode": "null",
      "percentage": false,
      "pointradius": 1,
      "points": true,
      "renderer": "flot",
      "seriesOverrides": [],
      "spaceLength": 10,
      "stack": false,
      "steppedLine": false,
      "targets": [
        {
          "groupBy": [
            {
              "params": [
                "$__interval"
              ],
              "type": "time"
            },
            {
              "params": [
                "process"
              ],
              "type": "tag"
            }
          ],
          "measurement": "LINUX_TOP_MEM",
          "orderByTime": "ASC",
          "policy": "default",
          "query": "SELECT mean(\"value\") FROM \"LINUX_TOP_MEM\" WHERE $timeFilter GROUP BY time($__interval), \"process\", \"host\"",
          "rawQuery": false,
          "refId": "B",
          "resultFormat": "time_series",
          "select": [
            [
              {
                "params": [
                  "value"
                ],
                "type": "field"
              },
              {
                "params": [],
                "type": "mean"
              }
            ]
          ],
          "tags": [
            {
              "key": "host",
              "operator": "=~",
              "value": "/^$host$/"
            }
          ]
        }
      ],
      "thresholds": [],
      "timeFrom": null,
      "timeShift": null,
      "title": "LINUX_TOP_MEM",
      "tooltip": {
        "shared": true,
        "sort": 0,
        "value_type": "individual"
      },
      "type": "graph",
      "xaxis": {
        "buckets": null,
        "mode": "time",
        "name": null,
        "show": true,
        "values": []
      },
      "yaxes": [
        {
          "format": "short",
          "label": null,
          "logBase": 1,
          "max": null,
          "min": null,
          "show": true
        },
        {
          "format": "short",
          "label": null,
          "logBase": 1,
          "max": null,
          "min": null,
          "show": true
        }
      ],
      "yaxis": {
        "align": false,
        "alignLevel": null
      }
    },
    {
      "aliasColors": {},
      "bars": false,
      "dashLength": 10,
      "dashes": false,
      "datasource": "${DS_INFLUX}",
      "decimals": null,
      "fill": 1,
      "gridPos": {
        "h": 9,
        "w": 12,
        "x": 12,
        "y": 36
      },
      "id": 12,
      "legend": {
        "alignAsTable": false,
        "avg": true,
        "current": false,
        "hideEmpty": false,
        "hideZero": false,
        "max": true,
        "min": false,
        "rightSide": false,
        "show": true,
        "total": false,
        "values": true
      },
      "lines": true,
      "linewidth": 1,
      "links": [],
      "nullPointMode": "null",
      "percentage": false,
      "pointradius": 1,
      "points": true,
      "renderer": "flot",
      "repeat": null,
      "seriesOverrides": [],
      "spaceLength": 10,
      "stack": false,
      "steppedLine": false,
      "targets": [
        {
          "groupBy": [
            {
              "params": [
                "$__interval"
              ],
              "type": "time"
            },
            {
              "params": [
                "type"
              ],
              "type": "tag"
            }
          ],
          "measurement": "LINUX_FREE",
          "orderByTime": "ASC",
          "policy": "default",
          "query": "SELECT mean(\"value\") FROM \"LINUX_FREE\" WHERE $timeFilter GROUP BY time($__interval), \"host\", \"type\"",
          "rawQuery": false,
          "refId": "S",
          "resultFormat": "time_series",
          "select": [
            [
              {
                "params": [
                  "value"
                ],
                "type": "field"
              },
              {
                "params": [],
                "type": "mean"
              }
            ]
          ],
          "tags": [
            {
              "key": "host",
              "operator": "=~",
              "value": "/^$host$/"
            }
          ]
        }
      ],
      "thresholds": [],
      "timeFrom": null,
      "timeShift": null,
      "title": "LINUX_FREE",
      "tooltip": {
        "shared": true,
        "sort": 1,
        "value_type": "individual"
      },
      "transparent": false,
      "type": "graph",
      "xaxis": {
        "buckets": null,
        "mode": "time",
        "name": null,
        "show": true,
        "values": []
      },
      "yaxes": [
        {
          "format": "kbytes",
          "label": "Memory in MB",
          "logBase": 1,
          "max": null,
          "min": null,
          "show": true
        },
        {
          "format": "deckbytes",
          "label": null,
          "logBase": 1,
          "max": null,
          "min": null,
          "show": true
        }
      ],
      "yaxis": {
        "align": false,
        "alignLevel": null
      }
    },
    {
      "collapsed": false,
      "gridPos": {
        "h": 1,
        "w": 24,
        "x": 0,
        "y": 45
      },
      "id": 40,
      "panels": [],
      "title": "CPU Overview",
      "type": "row"
    },
    {
      "aliasColors": {},
      "bars": false,
      "dashLength": 10,
      "dashes": false,
      "datasource": "${DS_INFLUX}",
      "fill": 1,
      "gridPos": {
        "h": 9,
        "w": 12,
        "x": 0,
        "y": 46
      },
      "id": 14,
      "legend": {
        "avg": true,
        "current": false,
        "max": true,
        "min": false,
        "show": true,
        "total": false,
        "values": true
      },
      "lines": true,
      "linewidth": 1,
      "links": [],
      "nullPointMode": "null",
      "percentage": false,
      "pointradius": 1,
      "points": true,
      "renderer": "flot",
      "seriesOverrides": [],
      "spaceLength": 10,
      "stack": false,
      "steppedLine": false,
      "targets": [
        {
          "groupBy": [
            {
              "params": [
                "$__interval"
              ],
              "type": "time"
            },
            {
              "params": [
                "process"
              ],
              "type": "tag"
            }
          ],
          "measurement": "LINUX_TOP_CPU",
          "orderByTime": "ASC",
          "policy": "default",
          "query": "SELECT mean(\"value\") FROM \"LINUX_TOP_CPU\" WHERE $timeFilter GROUP BY time($__interval), \"process\", \"host\"",
          "rawQuery": false,
          "refId": "A",
          "resultFormat": "time_series",
          "select": [
            [
              {
                "params": [
                  "value"
                ],
                "type": "field"
              },
              {
                "params": [],
                "type": "mean"
              }
            ]
          ],
          "tags": [
            {
              "key": "host",
              "operator": "=~",
              "value": "/^$host$/"
            }
          ]
        }
      ],
      "thresholds": [],
      "timeFrom": null,
      "timeShift": null,
      "title": "LINUX_TOP_CPU",
      "tooltip": {
        "shared": true,
        "sort": 0,
        "value_type": "individual"
      },
      "type": "graph",
      "xaxis": {
        "buckets": null,
        "mode": "time",
        "name": null,
        "show": true,
        "values": []
      },
      "yaxes": [
        {
          "format": "short",
          "label": null,
          "logBase": 1,
          "max": null,
          "min": null,
          "show": true
        },
        {
          "format": "short",
          "label": null,
          "logBase": 1,
          "max": null,
          "min": null,
          "show": true
        }
      ],
      "yaxis": {
        "align": false,
        "alignLevel": null
      }
    },
    {
      "aliasColors": {},
      "bars": false,
      "dashLength": 10,
      "dashes": false,
      "datasource": "${DS_INFLUX}",
      "fill": 1,
      "gridPos": {
        "h": 9,
        "w": 12,
        "x": 12,
        "y": 46
      },
      "id": 16,
      "legend": {
        "avg": true,
        "current": false,
        "max": true,
        "min": false,
        "show": true,
        "total": false,
        "values": true
      },
      "lines": true,
      "linewidth": 1,
      "links": [],
      "nullPointMode": "null",
      "percentage": false,
      "pointradius": 5,
      "points": false,
      "renderer": "flot",
      "seriesOverrides": [],
      "spaceLength": 10,
      "stack": false,
      "steppedLine": false,
      "targets": [
        {
          "groupBy": [
            {
              "params": [
                "host"
              ],
              "type": "tag"
            },
            {
              "params": [
                "type"
              ],
              "type": "tag"
            }
          ],
          "measurement": "WIN_CPU",
          "orderByTime": "ASC",
          "policy": "default",
          "query": "SELECT \"value\" FROM \"WIN_NETSTAT\" WHERE $timeFilter GROUP BY time($__interval), \"host\"",
          "rawQuery": false,
          "refId": "A",
          "resultFormat": "time_series",
          "select": [
            [
              {
                "params": [
                  "value"
                ],
                "type": "field"
              }
            ]
          ],
          "tags": [],
          "target": ""
        }
      ],
      "thresholds": [],
      "timeFrom": null,
      "timeShift": null,
      "title": "WIN-CPU",
      "tooltip": {
        "shared": true,
        "sort": 0,
        "value_type": "individual"
      },
      "type": "graph",
      "xaxis": {
        "buckets": null,
        "mode": "time",
        "name": null,
        "show": true,
        "values": []
      },
      "yaxes": [
        {
          "format": "short",
          "label": null,
          "logBase": 1,
          "max": null,
          "min": null,
          "show": true
        },
        {
          "format": "short",
          "label": null,
          "logBase": 1,
          "max": null,
          "min": null,
          "show": true
        }
      ],
      "yaxis": {
        "align": false,
        "alignLevel": null
      }
    }
  ],
  "refresh": false,
  "schemaVersion": 16,
  "style": "dark",
  "tags": [],
  "templating": {
    "list": [
      {
        "allValue": null,
        "current": {},
        "datasource": "${DS_INFLUX}",
        "hide": 0,
        "includeAll": true,
        "label": null,
        "multi": true,
        "name": "host",
        "options": [],
        "query": "show tag values from  LINUX_FREE with key = \"host\" ",
        "refresh": 1,
        "regex": "",
        "sort": 0,
        "tagValuesQuery": "",
        "tags": [],
        "tagsQuery": "",
        "type": "query",
        "useTags": false
      }
    ]
  },
  "time": {
    "from": "2018-09-06T03:03:27.867Z",
    "to": "2018-09-06T04:05:19.207Z"
  },
  "timepicker": {
    "hidden": false,
    "refresh_intervals": [
      "5s"
    ],
    "time_options": [
      "5m",
      "15m",
      "1h",
      "6h",
      "12h",
      "24h",
      "2d",
      "7d",
      "30d"
    ]
  },
  "timezone": "",
  "title": "System Monitoring",
  "uid": "mysAf8oik",
  "version": 13,
  "description": "This Grafana Dashboard helps to monitor OS level Statistics."
}